bitmex_websocket.py
main.py
util/__init__.py
util/api_key.py
util/subscriptions.py
bitmex_ws_alpha-0.4.2.dist-info/METADATA
bitmex_ws_alpha-0.4.2.dist-info/WHEEL
bitmex_ws_alpha-0.4.2.dist-info/top_level.txt
bitmex_ws_alpha-0.4.2.dist-info/RECORD
